esmerald_timing/__init__.py
esmerald_timing/integrations.py
esmerald_timing-0.1.0.dist-info/METADATA
esmerald_timing-0.1.0.dist-info/WHEEL
esmerald_timing-0.1.0.dist-info/licenses/LICENSE
esmerald_timing-0.1.0.dist-info/RECORD
