Metadata-Version: 2.1
Name: esmerald_timing
Version: 0.1.0
Summary: The scheduler that nobody wants but every application needs.
Project-URL: Homepage, https://github.com/dymmond/esmerald-timing
Project-URL: Documentation, https://github.com/dymmond/esmerald-timing
Project-URL: Changelog, https://dymmond.com/esmerald-timing/changelog/
Project-URL: Funding, https://github.com/sponsors/tarsil
Project-URL: Source, https://github.com/dymmond/esmerald-timing
Author-email: Tiago Silva <tiago.arasilva@gmail.com>
License-Expression: MIT
License-File: LICENSE
Keywords: api,apscheduler,asgi,cron,esmerald,fastapi,framework,http,machine learning,ml,openapi,pydantic,rest,scheduler,starlette,websocket
Classifier: Development Status :: 4 - Beta
Classifier: Environment :: Web Environment
Classifier: Framework :: AnyIO
Classifier: Framework :: AsyncIO
Classifier: Intended Audience :: Developers
Classifier: Intended Audience :: Information Technology
Classifier: Intended Audience :: System Administrators
Classifier: License :: OSI Approved :: MIT License
Classifier: Operating System :: OS Independent
Classifier: Programming Language :: Python
Classifier: Programming Language :: Python :: 3
Classifier: Programming Language :: Python :: 3 :: Only
Classifier: Programming Language :: Python :: 3.7
Classifier: Programming Language :: Python :: 3.8
Classifier: Programming Language :: Python :: 3.9
Classifier: Programming Language :: Python :: 3.10
Classifier: Topic :: Internet
Classifier: Topic :: Internet :: WWW/HTTP
Classifier: Topic :: Internet :: WWW/HTTP :: HTTP Servers
Classifier: Topic :: Software Development
Classifier: Topic :: Software Development :: Libraries
Classifier: Topic :: Software Development :: Libraries :: Application Frameworks
Classifier: Topic :: Software Development :: Libraries :: Python Modules
Classifier: Typing :: Typed
Requires-Python: >=3.7
Requires-Dist: asyncio<4.0.0,>=3.4.3
Provides-Extra: all
Requires-Dist: timing-asgi<4.0.0,>=0.3.0; extra == 'all'
Provides-Extra: dev
Requires-Dist: autoflake<3.0.0,>=1.4.0; extra == 'dev'
Requires-Dist: black<23.0.0,>=22.10.0; extra == 'dev'
Requires-Dist: flake8<7.0.0,>=3.8.3; extra == 'dev'
Requires-Dist: isort<6.0.0,>=5.0.6; extra == 'dev'
Requires-Dist: mypy<2.0.0,>=0.982; extra == 'dev'
Requires-Dist: pre-commit<3.0.0,>=2.17.0; extra == 'dev'
Requires-Dist: watchfiles<0.20.0,>=0.16.1; extra == 'dev'
Provides-Extra: test
Requires-Dist: asynctest<1.0.0,>=0.13.0; extra == 'test'
Requires-Dist: esmerald>=0.5.4; extra == 'test'
Requires-Dist: pytest-cov<5.0.0,>=2.12.0; extra == 'test'
Requires-Dist: pytest<8.0.0,>=7.1.3; extra == 'test'
